<?xml version="1.0" encoding="UTF-8"?>
<!DOCTYPE QtCreatorCMakeTools>
<!-- Written by QtCreator 4.6.2, 2018-10-17T13:56:11. -->
<qtcreator>
 <data>
  <variable>CMakeTools.0</variable>
  <valuemap type="QVariantMap">
   <value type="bool" key="AutoCreateBuildDirectory">false</value>
   <value type="bool" key="AutoDetected">true</value>
   <value type="bool" key="AutoRun">true</value>
   <value type="QString" key="Binary">/bin/cmake</value>
   <value type="QString" key="DisplayName">System CMake at /bin/cmake</value>
   <value type="QString" key="Id">{89b671b7-ee77-4c51-b970-67403e3a8a65}</value>
  </valuemap>
 </data>
 <data>
  <variable>CMakeTools.1</variable>
  <valuemap type="QVariantMap">
   <value type="bool" key="AutoCreateBuildDirectory">false</value>
   <value type="bool" key="AutoDetected">true</value>
   <value type="bool" key="AutoRun">true</value>
   <value type="QString" key="Binary">/usr/bin/cmake</value>
   <value type="QString" key="DisplayName">System CMake at /usr/bin/cmake</value>
   <value type="QString" key="Id">{fc3e2fc2-e302-4fba-8530-f60265997891}</value>
  </valuemap>
 </data>
 <data>
  <variable>CMakeTools.Count</variable>
  <value type="int">2</value>
 </data>
 <data>
  <variable>CMakeTools.Default</variable>
  <value type="QString">{fc3e2fc2-e302-4fba-8530-f60265997891}</value>
 </data>
 <data>
  <variable>Version</variable>
  <value type="int">1</value>
 </data>
</qtcreator>
